<PropertyList>
    <name type="string" n="0">take-off</name>
    <overlay>
	<controls>
	    <flight>
		<elevator-trim>-0.22</elevator-trim>
		<flaps>0.5</flaps>
		<speedbrake>0.0</speedbrake>
		<wing-fold>
		    <handle-cmd>0</handle-cmd>
		    <lockpin-cmd>0</lockpin-cmd>
		</wing-fold>
	    </flight>
	    <gear>
		<tailhook>false</tailhook>
		<gear-down>true</gear-down>
		<parking-brake>0.0</parking-brake>
	    </gear>
	    <lighting>
		<beacon>1</beacon>
		<taxi-light>0</taxi-light>
	    </lighting>
	    
	    <engines>
                <engine n="0">
                    <cutoff type="bool">false</cutoff>
                    <starter type="bool">false</starter>
                </engine>
		<engine n="1">
		    <cutoff type="bool">false</cutoff>
                    <starter type="bool">false</starter>
                </engine>
            </engines>
	</controls>

	<engines>
            <engine n="0">
                <running type="bool">true</running>
            </engine>
            <engine n="1">
                <running type="bool">true</running>
            </engine>
        </engines>

	<canopy>
	    <position-norm>0.0</position-norm>
	</canopy>

	<fdm>
	    <jsbsim>
		<fcs>
		    <wing-fold>
			<lockpin>1</lockpin>
		    </wing-fold>
		</fcs>
	    </jsbsim>
	</fdm>
    </overlay>
</PropertyList>
